<?xml version="1.0" encoding="utf-8" ?>
<root>

	<!-- New Sounds -->
	
	<!-- Leader -->
	<ID>VoicesLeader\LEADER_Yes_rnd_20</ID>
	<ID>VoicesLeader\LEADER_Yes_rnd_19</ID>
	<ID>VoicesLeader\LEADER_Yes_rnd_18</ID>
	<ID>VoicesLeader\LEADER_Yes_rnd_17</ID>
	<ID>VoicesLeader\LEADER_Yes_rnd_16</ID>
	<ID>VoicesLeader\LEADER_Yes_rnd_15</ID>
	<ID>VoicesLeader\LEADER_Yes_rnd_14</ID>
	<ID>VoicesLeader\LEADER_Yes_rnd_13</ID>
	<ID>VoicesLeader\LEADER_Yes_rnd_12</ID>
	<ID>VoicesLeader\LEADER_Yes_rnd_11</ID>
	<ID>VoicesLeader\LEADER_Yes_rnd_10</ID>
	<ID>VoicesLeader\LEADER_Yes_rnd_09</ID>
	<ID>VoicesLeader\LEADER_Yes_rnd_08</ID>
	<ID>VoicesLeader\LEADER_Yes_rnd_07</ID>
	<ID>VoicesLeader\LEADER_Yes_rnd_06</ID>
	<ID>VoicesLeader\LEADER_Yes_rnd_05</ID>
	<ID>VoicesLeader\LEADER_Yes_rnd_04</ID>
	<ID>VoicesLeader\LEADER_Yes_rnd_03</ID>
	<ID>VoicesLeader\LEADER_Yes_rnd_02</ID>
	<ID>VoicesLeader\LEADER_Yes_rnd_01</ID>
	<ID>VoicesLeader\LEADER_Stand_rnd_03</ID>
	<ID>VoicesLeader\LEADER_Stand_rnd_02</ID>
	<ID>VoicesLeader\LEADER_Stand_rnd_01</ID>
	<ID>VoicesLeader\LEADER_Patrol_rnd_03</ID>
	<ID>VoicesLeader\LEADER_Patrol_rnd_02</ID>
	<ID>VoicesLeader\LEADER_Patrol_rnd_01</ID>
	<ID>VoicesLeader\LEADER_NO_rnd_10</ID>
	<ID>VoicesLeader\LEADER_NO_rnd_09</ID>
	<ID>VoicesLeader\LEADER_NO_rnd_08</ID>
	<ID>VoicesLeader\LEADER_NO_rnd_07</ID>
	<ID>VoicesLeader\LEADER_NO_rnd_06</ID>
	<ID>VoicesLeader\LEADER_NO_rnd_05</ID>
	<ID>VoicesLeader\LEADER_NO_rnd_04</ID>
	<ID>VoicesLeader\LEADER_NO_rnd_03</ID>
	<ID>VoicesLeader\LEADER_NO_rnd_02</ID>
	<ID>VoicesLeader\LEADER_NO_rnd_01</ID>
	<ID>VoicesLeader\LEADER_Guard_rnd_03</ID>
	<ID>VoicesLeader\LEADER_Guard_rnd_02</ID>
	<ID>VoicesLeader\LEADER_Guard_rnd_01</ID>
	<ID>VoicesLeader\LEADER_FunnyComment_rnd_04</ID>
	<ID>VoicesLeader\LEADER_FunnyComment_rnd_03</ID>
	<ID>VoicesLeader\LEADER_FunnyComment_rnd_02</ID>
	<ID>VoicesLeader\LEADER_FunnyComment_rnd_01</ID>
	<ID>VoicesLeader\LEADER_Defend_rnd_03</ID>
	<ID>VoicesLeader\LEADER_Defend_rnd_02</ID>
	<ID>VoicesLeader\LEADER_Defend_rnd_01</ID>
	<ID>VoicesLeader\LEADER_ChangeFormation_rnd_08</ID>
	<ID>VoicesLeader\LEADER_ChangeFormation_rnd_07</ID>
	<ID>VoicesLeader\LEADER_ChangeFormation_rnd_06</ID>
	<ID>VoicesLeader\LEADER_ChangeFormation_rnd_05</ID>
	<ID>VoicesLeader\LEADER_ChangeFormation_rnd_04</ID>
	<ID>VoicesLeader\LEADER_ChangeFormation_rnd_03</ID>
	<ID>VoicesLeader\LEADER_ChangeFormation_rnd_02</ID>
	<ID>VoicesLeader\LEADER_ChangeFormation_rnd_01</ID>
	<ID>VoicesLeader\LEADER_Attack_rnd_10</ID>
	<ID>VoicesLeader\LEADER_Attack_rnd_09</ID>
	<ID>VoicesLeader\LEADER_Attack_rnd_08</ID>
	<ID>VoicesLeader\LEADER_Attack_rnd_07</ID>
	<ID>VoicesLeader\LEADER_Attack_rnd_06</ID>
	<ID>VoicesLeader\LEADER_Attack_rnd_05</ID>
	<ID>VoicesLeader\LEADER_Attack_rnd_04</ID>
	<ID>VoicesLeader\LEADER_Attack_rnd_03</ID>
	<ID>VoicesLeader\LEADER_Attack_rnd_02</ID>
	<ID>VoicesLeader\LEADER_Attack_rnd_01</ID>
	<ID>VoicesLeader\LEADER_Selection_rnd_04</ID>
	<ID>VoicesLeader\LEADER_Selection_rnd_03</ID>
	<ID>VoicesLeader\LEADER_Selection_rnd_02</ID>
	<ID>VoicesLeader\LEADER_Selection_rnd_01</ID>
	
	
	<!-- Heroes -->
	<ID>VoicesHero1\HERO1_Attack_rnd_01</ID>
	<ID>VoicesHero1\HERO1_Attack_rnd_02</ID>
	<ID>VoicesHero1\HERO1_Attack_rnd_03</ID>
	<ID>VoicesHero1\HERO1_Attack_rnd_04</ID>
	<ID>VoicesHero1\HERO1_Attack_rnd_05</ID>
	<ID>VoicesHero1\HERO1_FunnyComment_rnd_01</ID>
	<ID>VoicesHero1\HERO1_FunnyComment_rnd_02</ID>
	<ID>VoicesHero1\HERO1_FunnyComment_rnd_03</ID>
	<ID>VoicesHero1\HERO1_FunnyComment_rnd_04</ID>
	<ID>VoicesHero1\HERO1_NO_rnd_01</ID>
	<ID>VoicesHero1\HERO1_NO_rnd_02</ID>
	<ID>VoicesHero1\HERO1_NO_rnd_03</ID>
	<ID>VoicesHero1\HERO1_NO_rnd_04</ID>
	<ID>VoicesHero1\HERO1_NO_rnd_05</ID>
	<ID>VoicesHero1\HERO1_NO_rnd_06</ID>
	<ID>VoicesHero1\HERO1_NO_rnd_07</ID>
	<ID>VoicesHero1\HERO1_ProtectPeople_rnd_01</ID>
	<ID>VoicesHero1\HERO1_ProtectPeople_rnd_02</ID>
	<ID>VoicesHero1\HERO1_ProtectPeople_rnd_03</ID>
	<ID>VoicesHero1\HERO1_ProtectPeople_rnd_04</ID>
	<ID>VoicesHero1\HERO1_SeeThruHawksEyes_rnd_01</ID>
	<ID>VoicesHero1\HERO1_SeeThruHawksEyes_rnd_02</ID>
	<ID>VoicesHero1\HERO1_SendHawk_rnd_01</ID>
	<ID>VoicesHero1\HERO1_SendHawk_rnd_02</ID>
	<ID>VoicesHero1\HERO1_SendHawk_rnd_03</ID>
	<ID>VoicesHero1\HERO1_SendHawk_rnd_04</ID>
	<ID>VoicesHero1\HERO1_Yes_rnd_01</ID>
	<ID>VoicesHero1\HERO1_Yes_rnd_02</ID>
	<ID>VoicesHero1\HERO1_Yes_rnd_04</ID>
	<ID>VoicesHero1\HERO1_Yes_rnd_05</ID>
	<ID>VoicesHero1\HERO1_Yes_rnd_06</ID>
	<ID>VoicesHero1\HERO1_Yes_rnd_07</ID>
	<ID>VoicesHero1\HERO1_Yes_rnd_08</ID>
	<ID>VoicesHero1\HERO1_Yes_rnd_09</ID>
	<ID>VoicesHero1\HERO1_Yes_rnd_10</ID>
	<ID>VoicesHero1\HERO1_Selection_rnd_01</ID>
	<ID>VoicesHero1\HERO1_Selection_rnd_02</ID>
	<ID>VoicesHero1\HERO1_Selection_rnd_03</ID>
	
	<ID>VoicesHero2\HERO2_Attack_rnd_01</ID>
	<ID>VoicesHero2\HERO2_Attack_rnd_02</ID>
	<ID>VoicesHero2\HERO2_Attack_rnd_03</ID>
	<ID>VoicesHero2\HERO2_Attack_rnd_04</ID>
	<ID>VoicesHero2\HERO2_Attack_rnd_05</ID>
	<ID>VoicesHero2\HERO2_BuildCannon_rnd_01</ID>
	<ID>VoicesHero2\HERO2_BuildCannon_rnd_02</ID>
	<ID>VoicesHero2\HERO2_BuildCannon_rnd_03</ID>
	<ID>VoicesHero2\HERO2_BuildCannon_rnd_04</ID>
	<ID>VoicesHero2\HERO2_FunnyComment_rnd_01</ID>
	<ID>VoicesHero2\HERO2_FunnyComment_rnd_02</ID>
	<ID>VoicesHero2\HERO2_FunnyComment_rnd_03</ID>
	<ID>VoicesHero2\HERO2_FunnyComment_rnd_04</ID>
	<ID>VoicesHero2\HERO2_NO_rnd_01</ID>
	<ID>VoicesHero2\HERO2_NO_rnd_02</ID>
	<ID>VoicesHero2\HERO2_NO_rnd_03</ID>
	<ID>VoicesHero2\HERO2_NO_rnd_04</ID>
	<ID>VoicesHero2\HERO2_NO_rnd_05</ID>
	<ID>VoicesHero2\HERO2_NO_rnd_06</ID>
	<ID>VoicesHero2\HERO2_NO_rnd_07</ID>
	<ID>VoicesHero2\HERO2_PlaceBomb_rnd_01</ID>
	<ID>VoicesHero2\HERO2_PlaceBomb_rnd_02</ID>
	<ID>VoicesHero2\HERO2_PlaceBomb_rnd_03</ID>
	<ID>VoicesHero2\HERO2_PlaceBomb_rnd_04</ID>
	<ID>VoicesHero2\HERO2_Yes_rnd_01</ID>
	<ID>VoicesHero2\HERO2_Yes_rnd_02</ID>
	<ID>VoicesHero2\HERO2_Yes_rnd_04</ID>
	<ID>VoicesHero2\HERO2_Yes_rnd_05</ID>
	<ID>VoicesHero2\HERO2_Yes_rnd_06</ID>
	<ID>VoicesHero2\HERO2_Yes_rnd_07</ID>
	<ID>VoicesHero2\HERO2_Yes_rnd_08</ID>
	<ID>VoicesHero2\HERO2_Yes_rnd_09</ID>
	<ID>VoicesHero2\HERO2_Yes_rnd_10</ID>
	<ID>VoicesHero2\HERO2_Selection_rnd_01</ID>
	<ID>VoicesHero2\HERO2_Selection_rnd_02</ID>
	<ID>VoicesHero2\HERO2_Selection_rnd_03</ID>
	
	<ID>VoicesHero3\HERO3_Attack_rnd_01</ID>
	<ID>VoicesHero3\HERO3_Attack_rnd_02</ID>
	<ID>VoicesHero3\HERO3_Attack_rnd_03</ID>
	<ID>VoicesHero3\HERO3_Attack_rnd_04</ID>
	<ID>VoicesHero3\HERO3_Attack_rnd_05</ID>
	<ID>VoicesHero3\HERO3_BuildTrap_rnd_01</ID>
	<ID>VoicesHero3\HERO3_BuildTrap_rnd_02</ID>
	<ID>VoicesHero3\HERO3_BuildTrap_rnd_03</ID>
	<ID>VoicesHero3\HERO3_BuildTrap_rnd_04</ID>
	<ID>VoicesHero3\HERO3_FunnyComment_rnd_01</ID>
	<ID>VoicesHero3\HERO3_FunnyComment_rnd_02</ID>
	<ID>VoicesHero3\HERO3_FunnyComment_rnd_03</ID>
	<ID>VoicesHero3\HERO3_FunnyComment_rnd_04</ID>
	<ID>VoicesHero3\HERO3_Heal_rnd_01</ID>
	<ID>VoicesHero3\HERO3_Heal_rnd_02</ID>
	<ID>VoicesHero3\HERO3_Heal_rnd_03</ID>
	<ID>VoicesHero3\HERO3_Heal_rnd_04</ID>
	<ID>VoicesHero3\HERO3_NO_rnd_01</ID>
	<ID>VoicesHero3\HERO3_NO_rnd_02</ID>
	<ID>VoicesHero3\HERO3_NO_rnd_03</ID>
	<ID>VoicesHero3\HERO3_NO_rnd_04</ID>
	<ID>VoicesHero3\HERO3_NO_rnd_05</ID>
	<ID>VoicesHero3\HERO3_NO_rnd_06</ID>
	<ID>VoicesHero3\HERO3_NO_rnd_07</ID>
	<ID>VoicesHero3\HERO3_Yes_rnd_01</ID>
	<ID>VoicesHero3\HERO3_Yes_rnd_02</ID>
	<ID>VoicesHero3\HERO3_Yes_rnd_04</ID>
	<ID>VoicesHero3\HERO3_Yes_rnd_05</ID>
	<ID>VoicesHero3\HERO3_Yes_rnd_06</ID>
	<ID>VoicesHero3\HERO3_Yes_rnd_07</ID>
	<ID>VoicesHero3\HERO3_Yes_rnd_08</ID>
	<ID>VoicesHero3\HERO3_Yes_rnd_09</ID>
	<ID>VoicesHero3\HERO3_Yes_rnd_10</ID>
	<ID>VoicesHero3\HERO3_Selection_rnd_01</ID>
	<ID>VoicesHero3\HERO3_Selection_rnd_02</ID>
	
	
	<ID>VoicesHero4\HERO4_Attack_rnd_01</ID>
	<ID>VoicesHero4\HERO4_Attack_rnd_02</ID>
	<ID>VoicesHero4\HERO4_Attack_rnd_03</ID>
	<ID>VoicesHero4\HERO4_Attack_rnd_04</ID>
	<ID>VoicesHero4\HERO4_Attack_rnd_05</ID>
	<ID>VoicesHero4\HERO4_AuraOfWar_rnd_01</ID>
	<ID>VoicesHero4\HERO4_AuraOfWar_rnd_02</ID>
	<ID>VoicesHero4\HERO4_AuraOfWar_rnd_03</ID>
	<ID>VoicesHero4\HERO4_AuraOfWar_rnd_04</ID>
	<ID>VoicesHero4\HERO4_CircularAttack_rnd_01</ID>
	<ID>VoicesHero4\HERO4_CircularAttack_rnd_02</ID>
	<ID>VoicesHero4\HERO4_CircularAttack_rnd_03</ID>
	<ID>VoicesHero4\HERO4_CircularAttack_rnd_04</ID>
	<ID>VoicesHero4\HERO4_FunnyComment_rnd_01</ID>
	<ID>VoicesHero4\HERO4_FunnyComment_rnd_02</ID>
	<ID>VoicesHero4\HERO4_FunnyComment_rnd_03</ID>
	<ID>VoicesHero4\HERO4_FunnyComment_rnd_04</ID>
	<ID>VoicesHero4\HERO4_NO_rnd_01</ID>
	<ID>VoicesHero4\HERO4_NO_rnd_02</ID>
	<ID>VoicesHero4\HERO4_NO_rnd_03</ID>
	<ID>VoicesHero4\HERO4_NO_rnd_04</ID>
	<ID>VoicesHero4\HERO4_NO_rnd_05</ID>
	<ID>VoicesHero4\HERO4_NO_rnd_06</ID>
	<ID>VoicesHero4\HERO4_NO_rnd_07</ID>
	<ID>VoicesHero4\HERO4_Yes_rnd_01</ID>
	<ID>VoicesHero4\HERO4_Yes_rnd_02</ID>
	<ID>VoicesHero4\HERO4_Yes_rnd_04</ID>
	<ID>VoicesHero4\HERO4_Yes_rnd_05</ID>
	<ID>VoicesHero4\HERO4_Yes_rnd_06</ID>
	<ID>VoicesHero4\HERO4_Yes_rnd_07</ID>
	<ID>VoicesHero4\HERO4_Yes_rnd_08</ID>
	<ID>VoicesHero4\HERO4_Yes_rnd_09</ID>
	<ID>VoicesHero4\HERO4_Yes_rnd_10</ID>
	<ID>VoicesHero4\HERO4_Selection_rnd_01</ID>
	<ID>VoicesHero4\HERO4_Selection_rnd_02</ID>
	<ID>VoicesHero4\HERO4_Selection_rnd_03</ID>
	


	<ID>VoicesHero6\HERO6_Attack_rnd_01</ID>
	<ID>VoicesHero6\HERO6_Attack_rnd_02</ID>
	<ID>VoicesHero6\HERO6_Attack_rnd_03</ID>
	<ID>VoicesHero6\HERO6_Attack_rnd_04</ID>
	<ID>VoicesHero6\HERO6_Attack_rnd_05</ID>
	<ID>VoicesHero6\HERO6_Bless_rnd_01</ID>
	<ID>VoicesHero6\HERO6_Bless_rnd_02</ID>
	<ID>VoicesHero6\HERO6_Bless_rnd_03</ID>
	<ID>VoicesHero6\HERO6_Bless_rnd_04</ID>
	<ID>VoicesHero6\HERO6_ConvertSettler_rnd_01</ID>
	<ID>VoicesHero6\HERO6_ConvertSettler_rnd_02</ID>
	<ID>VoicesHero6\HERO6_ConvertSettler_rnd_03</ID>
	<ID>VoicesHero6\HERO6_ConvertSettler_rnd_04</ID>
	<ID>VoicesHero6\HERO6_FunnyComment_rnd_01</ID>
	<ID>VoicesHero6\HERO6_FunnyComment_rnd_02</ID>
	<ID>VoicesHero6\HERO6_FunnyComment_rnd_03</ID>
	<ID>VoicesHero6\HERO6_FunnyComment_rnd_04</ID>
	<ID>VoicesHero6\HERO6_NO_rnd_01</ID>
	<ID>VoicesHero6\HERO6_NO_rnd_02</ID>
	<ID>VoicesHero6\HERO6_NO_rnd_03</ID>
	<ID>VoicesHero6\HERO6_NO_rnd_04</ID>
	<ID>VoicesHero6\HERO6_NO_rnd_05</ID>
	<ID>VoicesHero6\HERO6_NO_rnd_06</ID>
	<ID>VoicesHero6\HERO6_NO_rnd_07</ID>
	<ID>VoicesHero6\HERO6_Yes_rnd_01</ID>
	<ID>VoicesHero6\HERO6_Yes_rnd_02</ID>
	<ID>VoicesHero6\HERO6_Yes_rnd_04</ID>
	<ID>VoicesHero6\HERO6_Yes_rnd_05</ID>
	<ID>VoicesHero6\HERO6_Yes_rnd_06</ID>
	<ID>VoicesHero6\HERO6_Yes_rnd_07</ID>
	<ID>VoicesHero6\HERO6_Yes_rnd_08</ID>
	<ID>VoicesHero6\HERO6_Yes_rnd_09</ID>
	<ID>VoicesHero6\HERO6_Yes_rnd_10</ID>
	<ID>VoicesHero6\HERO6_Selection_rnd_01</ID>
	<ID>VoicesHero6\HERO6_Selection_rnd_02</ID>
	
	
	<ID>VoicesHero7\HERO7_Attack_rnd_01</ID>
	<ID>VoicesHero7\HERO7_Attack_rnd_02</ID>
	<ID>VoicesHero7\HERO7_Attack_rnd_03</ID>
	<ID>VoicesHero7\HERO7_Attack_rnd_04</ID>
	<ID>VoicesHero7\HERO7_Attack_rnd_05</ID>
	<ID>VoicesHero7\HERO7_FunnyComment_rnd_01</ID>
	<ID>VoicesHero7\HERO7_FunnyComment_rnd_02</ID>
	<ID>VoicesHero7\HERO7_FunnyComment_rnd_03</ID>
	<ID>VoicesHero7\HERO7_FunnyComment_rnd_04</ID>
	<ID>VoicesHero7\HERO7_InflictFear_rnd_01</ID>
	<ID>VoicesHero7\HERO7_InflictFear_rnd_02</ID>
	<ID>VoicesHero7\HERO7_InflictFear_rnd_03</ID>
	<ID>VoicesHero7\HERO7_InflictFear_rnd_04</ID>
	<ID>VoicesHero7\HERO7_Madness_rnd_01</ID>
	<ID>VoicesHero7\HERO7_Madness_rnd_02</ID>
	<ID>VoicesHero7\HERO7_Madness_rnd_03</ID>
	<ID>VoicesHero7\HERO7_Madness_rnd_04</ID>
	<ID>VoicesHero7\HERO7_NO_rnd_01</ID>
	<ID>VoicesHero7\HERO7_NO_rnd_02</ID>
	<ID>VoicesHero7\HERO7_NO_rnd_03</ID>
	<ID>VoicesHero7\HERO7_NO_rnd_04</ID>
	<ID>VoicesHero7\HERO7_NO_rnd_05</ID>
	<ID>VoicesHero7\HERO7_NO_rnd_06</ID>
	<ID>VoicesHero7\HERO7_NO_rnd_07</ID>
	<ID>VoicesHero7\HERO7_Yes_rnd_01</ID>
	<ID>VoicesHero7\HERO7_Yes_rnd_02</ID>
	<ID>VoicesHero7\HERO7_Yes_rnd_04</ID>
	<ID>VoicesHero7\HERO7_Yes_rnd_05</ID>
	<ID>VoicesHero7\HERO7_Yes_rnd_06</ID>
	<ID>VoicesHero7\HERO7_Yes_rnd_07</ID>
	<ID>VoicesHero7\HERO7_Yes_rnd_08</ID>
	<ID>VoicesHero7\HERO7_Yes_rnd_09</ID>
	<ID>VoicesHero7\HERO7_Yes_rnd_10</ID>
	
	
	<ID>VoicesHero9\HERO9_Attack_rnd_01</ID>
	<ID>VoicesHero9\HERO9_Attack_rnd_02</ID>
	<ID>VoicesHero9\HERO9_Attack_rnd_03</ID>
	<ID>VoicesHero9\HERO9_Attack_rnd_04</ID>
	<ID>VoicesHero9\HERO9_Attack_rnd_05</ID>
	<ID>VoicesHero9\HERO9_Berserk_rnd_01</ID>
	<ID>VoicesHero9\HERO9_Berserk_rnd_02</ID>
	<ID>VoicesHero9\HERO9_Berserk_rnd_03</ID>
	<ID>VoicesHero9\HERO9_Berserk_rnd_04</ID>
	<ID>VoicesHero9\HERO9_CallWolfs_rnd_01</ID>
	<ID>VoicesHero9\HERO9_CallWolfs_rnd_02</ID>
	<ID>VoicesHero9\HERO9_CallWolfs_rnd_03</ID>
	<ID>VoicesHero9\HERO9_CallWolfs_rnd_04</ID>
	<ID>VoicesHero9\HERO9_FunnyComment_rnd_01</ID>
	<ID>VoicesHero9\HERO9_FunnyComment_rnd_02</ID>
	<ID>VoicesHero9\HERO9_FunnyComment_rnd_03</ID>
	<ID>VoicesHero9\HERO9_FunnyComment_rnd_04</ID>
	<ID>VoicesHero9\HERO9_NO_rnd_01</ID>
	<ID>VoicesHero9\HERO9_NO_rnd_02</ID>
	<ID>VoicesHero9\HERO9_NO_rnd_03</ID>
	<ID>VoicesHero9\HERO9_NO_rnd_04</ID>
	<ID>VoicesHero9\HERO9_NO_rnd_05</ID>
	<ID>VoicesHero9\HERO9_NO_rnd_06</ID>
	<ID>VoicesHero9\HERO9_NO_rnd_07</ID>
	<ID>VoicesHero9\HERO9_Yes_rnd_01</ID>
	<ID>VoicesHero9\HERO9_Yes_rnd_02</ID>
	<ID>VoicesHero9\HERO9_Yes_rnd_04</ID>
	<ID>VoicesHero9\HERO9_Yes_rnd_05</ID>
	<ID>VoicesHero9\HERO9_Yes_rnd_06</ID>
	<ID>VoicesHero9\HERO9_Yes_rnd_07</ID>
	<ID>VoicesHero9\HERO9_Yes_rnd_08</ID>
	<ID>VoicesHero9\HERO9_Yes_rnd_09</ID>
	<ID>VoicesHero9\HERO9_Yes_rnd_10</ID>
	<ID>VoicesHero9\HERO9_Selection_rnd_01</ID>
	<ID>VoicesHero9\HERO9_Selection_rnd_02</ID>

	
	
	<!-- Workers -->
	
	<ID>VoicesWorker\WORKER_FunnyComment_rnd_01</ID>
	<ID>VoicesWorker\WORKER_FunnyComment_rnd_02</ID>
	<ID>VoicesWorker\WORKER_FunnyComment_rnd_03</ID>
	<ID>VoicesWorker\WORKER_FunnyComment_rnd_04</ID>
	<ID>VoicesWorker\WORKER_FunnyComment_rnd_05</ID>
	<ID>VoicesWorker\WORKER_FunnyNo_rnd_01</ID>
	<ID>VoicesWorker\WORKER_FunnyNo_rnd_02</ID>
	<ID>VoicesWorker\WORKER_FunnyNo_rnd_03</ID>
	<ID>VoicesWorker\WORKER_FunnyNo_rnd_04</ID>
	<ID>VoicesWorker\WORKER_FunnyNo_rnd_05</ID>
	<ID>VoicesWorker\WORKER_FunnyNo_rnd_06</ID>
	<ID>VoicesWorker\WORKER_FunnyNo_rnd_07</ID>
	<ID>VoicesWorker\WORKER_FunnyNo_rnd_08</ID>
	<ID>VoicesWorker\WORKER_FunnyNo_rnd_09</ID>
	<ID>VoicesWorker\WORKER_FunnyNo_rnd_10</ID>
	<ID>VoicesWorker\WORKER_FunnyNo_rnd_11</ID>
	<ID>VoicesWorker\WORKER_FunnyNo_rnd_12</ID>
	<ID>VoicesWorker\WORKER_FunnyNo_rnd_13</ID>
	<ID>VoicesWorker\WORKER_FunnyNo_rnd_14</ID>
	<ID>VoicesWorker\WORKER_FunnyNo_rnd_15</ID>
	<ID>VoicesWorker\WORKER_FunnyNo_rnd_16</ID>
	<ID>VoicesWorker\WORKER_FunnyNo_rnd_17</ID>
	<ID>VoicesWorker\WORKER_FunnyNo_rnd_18</ID>
	<ID>VoicesWorker\WORKER_FunnyNo_rnd_19</ID>
	<ID>VoicesWorker\WORKER_FunnyNo_rnd_20</ID>
	<ID>VoicesWorker\WORKER_ILikeItHere_rnd_01</ID>
	<ID>VoicesWorker\WORKER_ILikeItHere_rnd_02</ID>
	<ID>VoicesWorker\WORKER_ILikeItHere_rnd_03</ID>
	<ID>VoicesWorker\WORKER_ILikeItHere_rnd_04</ID>
	<ID>VoicesWorker\WORKER_ILikeItHere_rnd_05</ID>
	<ID>VoicesWorker\WORKER_Leaving_rnd_01</ID>
	<ID>VoicesWorker\WORKER_Leaving_rnd_02</ID>
	<ID>VoicesWorker\WORKER_Leaving_rnd_03</ID>
	<ID>VoicesWorker\WORKER_Leaving_rnd_04</ID>
	<ID>VoicesWorker\WORKER_NeedBed_rnd_01</ID>
	<ID>VoicesWorker\WORKER_NeedBed_rnd_02</ID>
	<ID>VoicesWorker\WORKER_NeedBed_rnd_03</ID>
	<ID>VoicesWorker\WORKER_NeedBed_rnd_04</ID>
	<ID>VoicesWorker\WORKER_NeedFood_rnd_01</ID>
	<ID>VoicesWorker\WORKER_NeedFood_rnd_02</ID>
	<ID>VoicesWorker\WORKER_NeedFood_rnd_03</ID>
	<ID>VoicesWorker\WORKER_NeedFood_rnd_04</ID>
	<ID>VoicesWorker\WORKER_NoWork_rnd_01</ID>
	<ID>VoicesWorker\WORKER_NoWork_rnd_02</ID>
	<ID>VoicesWorker\WORKER_NoWork_rnd_03</ID>
	<ID>VoicesWorker\WORKER_NoWork_rnd_04</ID>
	<ID>VoicesWorker\WORKER_TaxesToHigh_rnd_01</ID>
	<ID>VoicesWorker\WORKER_TaxesToHigh_rnd_02</ID>
	<ID>VoicesWorker\WORKER_TaxesToHigh_rnd_03</ID>
	<ID>VoicesWorker\WORKER_TaxesToHigh_rnd_04</ID>
	<ID>VoicesWorker\WORKER_Unhappy_rnd_01</ID>
	<ID>VoicesWorker\WORKER_Unhappy_rnd_02</ID>
	<ID>VoicesWorker\WORKER_Unhappy_rnd_03</ID>
	<ID>VoicesWorker\WORKER_Unhappy_rnd_04</ID>
	<ID>VoicesWorker\WORKER_Unhappy_rnd_05</ID>


	<ID>VoicesHero5\HERO5_Attack_rnd_01</ID>
	<ID>VoicesHero5\HERO5_Attack_rnd_02</ID>
	<ID>VoicesHero5\HERO5_Attack_rnd_03</ID>
	<ID>VoicesHero5\HERO5_Attack_rnd_04</ID>
	<ID>VoicesHero5\HERO5_Attack_rnd_05</ID>
	<ID>VoicesHero5\HERO5_CallBandits_rnd_01</ID>
	<ID>VoicesHero5\HERO5_CallBandits_rnd_02</ID>
	<ID>VoicesHero5\HERO5_CallBandits_rnd_03</ID>
	<ID>VoicesHero5\HERO5_CallBandits_rnd_04</ID>
	<ID>VoicesHero5\HERO5_Camouflage_rnd_01</ID>
	<ID>VoicesHero5\HERO5_Camouflage_rnd_02</ID>
	<ID>VoicesHero5\HERO5_Camouflage_rnd_03</ID>
	<ID>VoicesHero5\HERO5_Camouflage_rnd_04</ID>
	<ID>VoicesHero5\HERO5_FunnyComment_rnd_01</ID>
	<ID>VoicesHero5\HERO5_FunnyComment_rnd_02</ID>
	<ID>VoicesHero5\HERO5_FunnyComment_rnd_03</ID>
	<ID>VoicesHero5\HERO5_FunnyComment_rnd_04</ID>
	<ID>VoicesHero5\HERO5_NO_rnd_01</ID>
	<ID>VoicesHero5\HERO5_NO_rnd_02</ID>
	<ID>VoicesHero5\HERO5_NO_rnd_03</ID>
	<ID>VoicesHero5\HERO5_NO_rnd_04</ID>
	<ID>VoicesHero5\HERO5_NO_rnd_05</ID>
	<ID>VoicesHero5\HERO5_NO_rnd_06</ID>
	<ID>VoicesHero5\HERO5_NO_rnd_07</ID>
	<ID>VoicesHero5\HERO5_Yes_rnd_01</ID>
	<ID>VoicesHero5\HERO5_Yes_rnd_02</ID>
	<ID>VoicesHero5\HERO5_Yes_rnd_04</ID>
	<ID>VoicesHero5\HERO5_Yes_rnd_05</ID>
	<ID>VoicesHero5\HERO5_Yes_rnd_06</ID>
	<ID>VoicesHero5\HERO5_Yes_rnd_07</ID>
	<ID>VoicesHero5\HERO5_Yes_rnd_08</ID>
	<ID>VoicesHero5\HERO5_Yes_rnd_09</ID>
	<ID>VoicesHero5\HERO5_Yes_rnd_10</ID>
	<ID>VoicesHero5\HERO5_Selection_rnd_01</ID>
	<ID>VoicesHero5\HERO5_Selection_rnd_02</ID>
	
	
	<ID>VoicesHero8\HERO8_Attack_rnd_01</ID>
	<ID>VoicesHero8\HERO8_Attack_rnd_02</ID>
	<ID>VoicesHero8\HERO8_Attack_rnd_03</ID>
	<ID>VoicesHero8\HERO8_Attack_rnd_04</ID>
	<ID>VoicesHero8\HERO8_Attack_rnd_05</ID>
	<ID>VoicesHero8\HERO8_FunnyComment_rnd_01</ID>
	<ID>VoicesHero8\HERO8_FunnyComment_rnd_02</ID>
	<ID>VoicesHero8\HERO8_FunnyComment_rnd_03</ID>
	<ID>VoicesHero8\HERO8_FunnyComment_rnd_04</ID>
	<ID>VoicesHero8\HERO8_MoraleDamage_rnd_01</ID>
	<ID>VoicesHero8\HERO8_MoraleDamage_rnd_02</ID>
	<ID>VoicesHero8\HERO8_MoraleDamage_rnd_03</ID>
	<ID>VoicesHero8\HERO8_MoraleDamage_rnd_04</ID>
	<ID>VoicesHero8\HERO8_NO_rnd_01</ID>
	<ID>VoicesHero8\HERO8_NO_rnd_02</ID>
	<ID>VoicesHero8\HERO8_NO_rnd_03</ID>
	<ID>VoicesHero8\HERO8_NO_rnd_04</ID>
	<ID>VoicesHero8\HERO8_NO_rnd_05</ID>
	<ID>VoicesHero8\HERO8_NO_rnd_06</ID>
	<ID>VoicesHero8\HERO8_NO_rnd_07</ID>
	<ID>VoicesHero8\HERO8_PoisonAttack_rnd_01</ID>
	<ID>VoicesHero8\HERO8_PoisonAttack_rnd_02</ID>
	<ID>VoicesHero8\HERO8_PoisonAttack_rnd_03</ID>
	<ID>VoicesHero8\HERO8_PoisonAttack_rnd_04</ID>
	<ID>VoicesHero8\HERO8_Yes_rnd_01</ID>
	<ID>VoicesHero8\HERO8_Yes_rnd_02</ID>
	<ID>VoicesHero8\HERO8_Yes_rnd_04</ID>
	<ID>VoicesHero8\HERO8_Yes_rnd_05</ID>
	<ID>VoicesHero8\HERO8_Yes_rnd_06</ID>
	<ID>VoicesHero8\HERO8_Yes_rnd_07</ID>
	<ID>VoicesHero8\HERO8_Yes_rnd_08</ID>
	<ID>VoicesHero8\HERO8_Yes_rnd_09</ID>
	<ID>VoicesHero8\HERO8_Yes_rnd_10</ID>
	<ID>VoicesHero8\HERO8_Selection_rnd_01</ID>
	<ID>VoicesHero8\HERO8_Selection_rnd_02</ID>
	
	
	<ID>VoicesSerf\SERF_CanNotFindResources_rnd_01</ID>
	<ID>VoicesSerf\SERF_CanNotFindResources_rnd_02</ID>
	<ID>VoicesSerf\SERF_CanNotFindResources_rnd_03</ID>
	<ID>VoicesSerf\SERF_CanNotFindResources_rnd_04</ID>
	<ID>VoicesSerf\SERF_CanNotFindResources_rnd_05</ID>
	<ID>VoicesSerf\SERF_FunnyComment_rnd_01</ID>
	<ID>VoicesSerf\SERF_FunnyComment_rnd_02</ID>
	<ID>VoicesSerf\SERF_FunnyComment_rnd_03</ID>
	<ID>VoicesSerf\SERF_FunnyComment_rnd_04</ID>
	<ID>VoicesSerf\SERF_No_rnd_01</ID>
	<ID>VoicesSerf\SERF_No_rnd_02</ID>
	<ID>VoicesSerf\SERF_No_rnd_03</ID>
	<ID>VoicesSerf\SERF_No_rnd_04</ID>
	<ID>VoicesSerf\SERF_No_rnd_05</ID>
	<ID>VoicesSerf\SERF_No_rnd_06</ID>
	<ID>VoicesSerf\SERF_No_rnd_07</ID>
	<ID>VoicesSerf\SERF_No_rnd_08</ID>
	<ID>VoicesSerf\SERF_No_rnd_09</ID>
	<ID>VoicesSerf\SERF_No_rnd_10</ID>
	<ID>VoicesSerf\SERF_WorkIsDone_rnd_01</ID>
	<ID>VoicesSerf\SERF_WorkIsDone_rnd_02</ID>
	<ID>VoicesSerf\SERF_WorkIsDone_rnd_03</ID>
	<ID>VoicesSerf\SERF_WorkIsDone_rnd_04</ID>
	<ID>VoicesSerf\SERF_WorkIsDone_rnd_05</ID>
	<ID>VoicesSerf\SERF_Yes_rnd_01</ID>
	<ID>VoicesSerf\SERF_Yes_rnd_02</ID>
	<ID>VoicesSerf\SERF_Yes_rnd_03</ID>
	<ID>VoicesSerf\SERF_Yes_rnd_04</ID>
	<ID>VoicesSerf\SERF_Yes_rnd_05</ID>
	<ID>VoicesSerf\SERF_Yes_rnd_06</ID>
	<ID>VoicesSerf\SERF_Yes_rnd_07</ID>
	<ID>VoicesSerf\SERF_Yes_rnd_08</ID>
	<ID>VoicesSerf\SERF_Yes_rnd_09</ID>
	<ID>VoicesSerf\SERF_Yes_rnd_10</ID>
	<ID>VoicesSerf\SERF_Yes_rnd_11</ID>
	<ID>VoicesSerf\SERF_Yes_rnd_12</ID>
	<ID>VoicesSerf\SERF_Yes_rnd_13</ID>
	<ID>VoicesSerf\SERF_Yes_rnd_14</ID>
	<ID>VoicesSerf\SERF_Yes_rnd_15</ID>
	<ID>VoicesSerf\SERF_Yes_rnd_16</ID>
	<ID>VoicesSerf\SERF_Yes_rnd_17</ID>
	<ID>VoicesSerf\SERF_Yes_rnd_18</ID>
	<ID>VoicesSerf\SERF_Yes_rnd_19</ID>
	<ID>VoicesSerf\SERF_Yes_rnd_20</ID>
	<ID>VoicesSerf\SERF_Selection_rnd_01</ID>
	<ID>VoicesSerf\SERF_Selection_rnd_02</ID>
	<ID>VoicesSerf\SERF_Selection_rnd_03</ID>	
	<ID>VoicesSerf\SERF_Selection_rnd_05</ID>




	<ID>VoicesMentor\ALARM_ActivateAlarm</ID>
	<ID>VoicesMentor\ALARM_GetWeapons</ID>
	<ID>VoicesMentor\ALARM_GoBackToWork</ID>
	<ID>VoicesMentor\ALARM_QuitAlarm</ID>
	<ID>VoicesMentor\ATTACK_AlliedUnderAttack_rnd_01</ID>
	<ID>VoicesMentor\ATTACK_AlliedUnderAttack_rnd_02</ID>
	<ID>VoicesMentor\ATTACK_AlliedUnderAttack_rnd_03</ID>
	<ID>VoicesMentor\ATTACK_AlliedUnderAttack_rnd_04</ID>
	<ID>VoicesMentor\ATTACK_AlliedUnderAttack_rnd_05</ID>
	<ID>VoicesMentor\ATTACK_HeroUnderAttack_rnd_01</ID>
	<ID>VoicesMentor\ATTACK_HeroUnderAttack_rnd_02</ID>
	<ID>VoicesMentor\ATTACK_HeroUnderAttack_rnd_03</ID>
	<ID>VoicesMentor\ATTACK_HeroUnderAttack_rnd_04</ID>
	<ID>VoicesMentor\ATTACK_UnderAttack_rnd_01</ID>
	<ID>VoicesMentor\ATTACK_UnderAttack_rnd_02</ID>
	<ID>VoicesMentor\ATTACK_UnderAttack_rnd_03</ID>
	<ID>VoicesMentor\ATTACK_UnderAttack_rnd_04</ID>
	<ID>VoicesMentor\ATTACK_UnderAttack_rnd_05</ID>
	<ID>VoicesMentor\ATTACK_UnitsDrowned_rnd_01</ID>
	<ID>VoicesMentor\ATTACK_UnitsDrowned_rnd_02</ID>
	<ID>VoicesMentor\ATTACK_UnitsDrowned_rnd_03</ID>
	<ID>VoicesMentor\ATTACK_UnitsDrowned_rnd_04</ID>
	<ID>VoicesMentor\ATTACK_UnitsDrowned_rnd_05</ID>
	<ID>VoicesMentor\ATTACK_VillageUnderAttack_rnd_01</ID>
	<ID>VoicesMentor\ATTACK_VillageUnderAttack_rnd_02</ID>
	<ID>VoicesMentor\ATTACK_VillageUnderAttack_rnd_03</ID>
	<ID>VoicesMentor\ATTACK_VillageUnderAttack_rnd_04</ID>
	<ID>VoicesMentor\ATTACK_VillageUnderAttack_rnd_05</ID>
	<ID>VoicesMentor\ATTACK_WorkerUnderAttack_rnd_01</ID>
	<ID>VoicesMentor\ATTACK_WorkerUnderAttack_rnd_02</ID>
	<ID>VoicesMentor\ATTACK_WorkerUnderAttack_rnd_03</ID>
	<ID>VoicesMentor\ATTACK_WorkerUnderAttack_rnd_04</ID>
	<ID>VoicesMentor\CHEST_FoundTreasureChest_rnd_01</ID>
	<ID>VoicesMentor\CHEST_FoundTreasureChest_rnd_02</ID>
	<ID>VoicesMentor\CHEST_FoundTreasureChest_rnd_03</ID>
	<ID>VoicesMentor\CHEST_FoundTreasureChest_rnd_04</ID>
	<ID>VoicesMentor\CHEST_FoundTreasureChest_rnd_05</ID>
	<ID>VoicesMentor\COMMENT_BadPlay_rnd_01</ID>
	<ID>VoicesMentor\COMMENT_BadPlay_rnd_02</ID>
	<ID>VoicesMentor\COMMENT_BadPlay_rnd_03</ID>
	<ID>VoicesMentor\COMMENT_BadPlay_rnd_04</ID>
	<ID>VoicesMentor\COMMENT_BadPlay_rnd_05</ID>
	<ID>VoicesMentor\COMMENT_BadPlay_rnd_06</ID>
	<ID>VoicesMentor\COMMENT_BadPlay_rnd_07</ID>
	<ID>VoicesMentor\COMMENT_GoodFight_rnd_01</ID>
	<ID>VoicesMentor\COMMENT_GoodFight_rnd_02</ID>
	<ID>VoicesMentor\COMMENT_GoodFight_rnd_03</ID>
	<ID>VoicesMentor\COMMENT_GoodFight_rnd_04</ID>
	<ID>VoicesMentor\COMMENT_GoodFight_rnd_05</ID>
	<ID>VoicesMentor\COMMENT_GoodPlay_rnd_01</ID>
	<ID>VoicesMentor\COMMENT_GoodPlay_rnd_02</ID>
	<ID>VoicesMentor\COMMENT_GoodPlay_rnd_03</ID>
	<ID>VoicesMentor\COMMENT_GoodPlay_rnd_04</ID>
	<ID>VoicesMentor\COMMENT_GoodPlay_rnd_05</ID>
	<ID>VoicesMentor\COMMENT_GoodPlay_rnd_06</ID>
	<ID>VoicesMentor\COMMENT_GoodPlay_rnd_07</ID>
	<ID>VoicesMentor\COMMENT_GoodPlay_rnd_08</ID>
	<ID>VoicesMentor\COMMENT_GoodPlay_rnd_09</ID>
	<ID>VoicesMentor\COMMENT_GoodPlay_rnd_10</ID>
	<ID>VoicesMentor\COMMENT_IntroduceNewMentor</ID>
	<ID>VoicesMentor\HAPPY_Alchemist</ID>
	<ID>VoicesMentor\HAPPY_Brickworker</ID>
	<ID>VoicesMentor\HAPPY_Engineer</ID>
	<ID>VoicesMentor\HAPPY_Farmer</ID>
	<ID>VoicesMentor\HAPPY_Miner</ID>
	<ID>VoicesMentor\HAPPY_Priest</ID>
	<ID>VoicesMentor\HAPPY_Sawmillworker</ID>
	<ID>VoicesMentor\HAPPY_Scholar</ID>
	<ID>VoicesMentor\HAPPY_Settler</ID>
	<ID>VoicesMentor\HAPPY_Smelter</ID>
	<ID>VoicesMentor\HAPPY_Smith</ID>
	<ID>VoicesMentor\HAPPY_Stonecutter</ID>
	<ID>VoicesMentor\HAPPY_Trader</ID>
	<ID>VoicesMentor\HAPPY_Treasurer</ID>
	<ID>VoicesMentor\HERO_HeroDiedHero1_rnd_01</ID>
	<ID>VoicesMentor\HERO_HeroDiedHero1_rnd_02</ID>
	<ID>VoicesMentor\HERO_HeroDiedHero2_rnd_01</ID>
	<ID>VoicesMentor\HERO_HeroDiedHero2_rnd_02</ID>
	<ID>VoicesMentor\HERO_HeroDiedHero3_rnd_01</ID>
	<ID>VoicesMentor\HERO_HeroDiedHero3_rnd_02</ID>
	<ID>VoicesMentor\HERO_HeroDiedHero4_rnd_01</ID>
	<ID>VoicesMentor\HERO_HeroDiedHero4_rnd_02</ID>
	<ID>VoicesMentor\HERO_HeroDiedHero5_rnd_01</ID>
	<ID>VoicesMentor\HERO_HeroDiedHero5_rnd_02</ID>
	<ID>VoicesMentor\HERO_HeroDiedHero6_rnd_01</ID>
	<ID>VoicesMentor\HERO_HeroDiedHero6_rnd_02</ID>
	<ID>VoicesMentor\HERO_HeroDiedHero7_rnd_01</ID>
	<ID>VoicesMentor\HERO_HeroDiedHero7_rnd_02</ID>
	<ID>VoicesMentor\HERO_HeroDiedHero8_rnd_01</ID>
	<ID>VoicesMentor\HERO_HeroDiedHero8_rnd_02</ID>
	<ID>VoicesMentor\HERO_HeroDiedHero9_rnd_01</ID>
	<ID>VoicesMentor\HERO_HeroDiedHero9_rnd_02</ID>
	<ID>VoicesMentor\INFO_EngineersNeedMoreTime_rnd_01</ID>
	<ID>VoicesMentor\INFO_EngineersNeedMoreTime_rnd_02</ID>
	<ID>VoicesMentor\INFO_EngineersNeedMoreTime_rnd_03</ID>
	<ID>VoicesMentor\INFO_LeaderGainedExperience_rnd_01</ID>
	<ID>VoicesMentor\INFO_LeaderGainedExperience_rnd_02</ID>
	<ID>VoicesMentor\INFO_LeaderGainedExperience_rnd_03</ID>
	<ID>VoicesMentor\INFO_LeaderGainedExperience_rnd_04</ID>
	<ID>VoicesMentor\INFO_LeaderGainedExperience_rnd_05</ID>
	<ID>VoicesMentor\INFO_MonksNeedMoreTime_rnd_01</ID>
	<ID>VoicesMentor\INFO_MonksNeedMoreTime_rnd_02</ID>
	<ID>VoicesMentor\INFO_MonksNeedMoreTime_rnd_03</ID>
	<ID>VoicesMentor\INFO_NotEnough</ID>
	<ID>VoicesMentor\INFO_NotEnoughBeds_rnd_01</ID>
	<ID>VoicesMentor\INFO_NotEnoughBeds_rnd_02</ID>
	<ID>VoicesMentor\INFO_NotEnoughBeds_rnd_03</ID>
	<ID>VoicesMentor\INFO_NotEnoughBeds_rnd_04</ID>
	<ID>VoicesMentor\INFO_NotEnoughClay_rnd_01</ID>
	<ID>VoicesMentor\INFO_NotEnoughClay_rnd_02</ID>
	<ID>VoicesMentor\INFO_NotEnoughFood_rnd_01</ID>
	<ID>VoicesMentor\INFO_NotEnoughFood_rnd_02</ID>
	<ID>VoicesMentor\INFO_NotEnoughFood_rnd_03</ID>
	<ID>VoicesMentor\INFO_NotEnoughFood_rnd_04</ID>
	<ID>VoicesMentor\INFO_NotEnoughGold_rnd_01</ID>
	<ID>VoicesMentor\INFO_NotEnoughGold_rnd_02</ID>
	<ID>VoicesMentor\INFO_NotEnoughIron_rnd_01</ID>
	<ID>VoicesMentor\INFO_NotEnoughIron_rnd_02</ID>
	<ID>VoicesMentor\INFO_NotEnoughStone_rnd_01</ID>
	<ID>VoicesMentor\INFO_NotEnoughStone_rnd_02</ID>
	<ID>VoicesMentor\INFO_NotEnoughSulfur_rnd_01</ID>
	<ID>VoicesMentor\INFO_NotEnoughSulfur_rnd_02</ID>
	<ID>VoicesMentor\INFO_NotEnoughWood_rnd_01</ID>
	<ID>VoicesMentor\INFO_NotEnoughWood_rnd_02</ID>
	<ID>VoicesMentor\INFO_Payday_rnd_01</ID>
	<ID>VoicesMentor\INFO_Payday_rnd_02</ID>
	<ID>VoicesMentor\INFO_Payday_rnd_03</ID>
	<ID>VoicesMentor\INFO_Payday_rnd_04</ID>
	<ID>VoicesMentor\INFO_SettlersBlessed_rnd_01</ID>
	<ID>VoicesMentor\INFO_SettlersBlessed_rnd_02</ID>
	<ID>VoicesMentor\INFO_SettlersBlessed_rnd_03</ID>
	<ID>VoicesMentor\INFO_SettlersBlessed_rnd_04</ID>
	<ID>VoicesMentor\INFO_VillageCenterEmpty_rnd_01</ID>
	<ID>VoicesMentor\INFO_VillageCenterEmpty_rnd_02</ID>
	<ID>VoicesMentor\INFO_VillageCenterEmpty_rnd_03</ID>
	<ID>VoicesMentor\INFO_VillageCenterEmpty_rnd_04</ID>
	<ID>VoicesMentor\JOIN_Alchemist</ID>
	<ID>VoicesMentor\JOIN_Brickworker</ID>
	<ID>VoicesMentor\JOIN_Engineer</ID>
	<ID>VoicesMentor\JOIN_Farmer</ID>
	<ID>VoicesMentor\JOIN_Miner</ID>
	<ID>VoicesMentor\JOIN_Priest</ID>
	<ID>VoicesMentor\JOIN_Sawmillworker</ID>
	<ID>VoicesMentor\JOIN_Scholar</ID>
	<ID>VoicesMentor\JOIN_Settler</ID>
	<ID>VoicesMentor\JOIN_Smelter</ID>
	<ID>VoicesMentor\JOIN_Smith</ID>
	<ID>VoicesMentor\JOIN_Stonecutter</ID>
	<ID>VoicesMentor\JOIN_Trader</ID>
	<ID>VoicesMentor\JOIN_Treasurer</ID>
	<ID>VoicesMentor\LEAVE_Alchemist</ID>
	<ID>VoicesMentor\LEAVE_Brickworker</ID>
	<ID>VoicesMentor\LEAVE_Engineer</ID>
	<ID>VoicesMentor\LEAVE_Farmer</ID>
	<ID>VoicesMentor\LEAVE_Miner</ID>
	<ID>VoicesMentor\LEAVE_Priest</ID>
	<ID>VoicesMentor\LEAVE_Sawmillworker</ID>
	<ID>VoicesMentor\LEAVE_Scholar</ID>
	<ID>VoicesMentor\LEAVE_Settler</ID>
	<ID>VoicesMentor\LEAVE_Smelter</ID>
	<ID>VoicesMentor\LEAVE_Smith</ID>
	<ID>VoicesMentor\LEAVE_Stonecutter</ID>
	<ID>VoicesMentor\LEAVE_Trader</ID>
	<ID>VoicesMentor\LEAVE_Treasurer</ID>
	<ID>VoicesMentor\MAD_Alchemist</ID>
	<ID>VoicesMentor\MAD_Brickworker</ID>
	<ID>VoicesMentor\MAD_Engineer</ID>
	<ID>VoicesMentor\MAD_Farmer</ID>
	<ID>VoicesMentor\MAD_Miner</ID>
	<ID>VoicesMentor\MAD_Priest</ID>
	<ID>VoicesMentor\MAD_Sawmillworker</ID>
	<ID>VoicesMentor\MAD_Scholar</ID>
	<ID>VoicesMentor\MAD_Settler</ID>
	<ID>VoicesMentor\MAD_Smelter</ID>
	<ID>VoicesMentor\MAD_Smith</ID>
	<ID>VoicesMentor\MAD_Stonecutter</ID>
	<ID>VoicesMentor\MAD_Trader</ID>
	<ID>VoicesMentor\MAD_Treasurer</ID>
	<ID>VoicesMentor\MINE_MineEmptyClay</ID>
	<ID>VoicesMentor\MINE_MineEmptyIron</ID>
	<ID>VoicesMentor\MINE_MineEmptyStone</ID>
	<ID>VoicesMentor\MINE_MineEmptySulfur</ID>
	<ID>VoicesMentor\MINE_MineRunningLowClay</ID>
	<ID>VoicesMentor\MINE_MineRunningLowIron</ID>
	<ID>VoicesMentor\MINE_MineRunningLowStone</ID>
	<ID>VoicesMentor\MINE_MineRunningLowSulfur</ID>
	<ID>VoicesMentor\MP_PeaceTimeOver_rnd_01</ID>
	<ID>VoicesMentor\MP_PeaceTimeOver_rnd_02</ID>
	<ID>VoicesMentor\MP_PeaceTimeOver_rnd_03</ID>
	<ID>VoicesMentor\MP_TauntAttack</ID>
	<ID>VoicesMentor\MP_TauntAttackArea</ID>
	<ID>VoicesMentor\MP_TauntDefendArea</ID>
	<ID>VoicesMentor\MP_TauntFunny01</ID>
	<ID>VoicesMentor\MP_TauntFunny02</ID>
	<ID>VoicesMentor\MP_TauntFunny03</ID>
	<ID>VoicesMentor\MP_TauntFunny04</ID>
	<ID>VoicesMentor\MP_TauntFunny05</ID>
	<ID>VoicesMentor\MP_TauntHelpMe</ID>
	<ID>VoicesMentor\MP_TauntNeedClay</ID>
	<ID>VoicesMentor\MP_TauntNeedGold</ID>
	<ID>VoicesMentor\MP_TauntNeedIron</ID>
	<ID>VoicesMentor\MP_TauntNeedStone</ID>
	<ID>VoicesMentor\MP_TauntNeedSulfur</ID>
	<ID>VoicesMentor\MP_TauntNeedWood</ID>
	<ID>VoicesMentor\MP_TauntNo</ID>
	<ID>VoicesMentor\MP_TauntNow</ID>
	<ID>VoicesMentor\MP_TauntVeryGood</ID>
	<ID>VoicesMentor\MP_TauntYes</ID>
	<ID>VoicesMentor\MP_TauntYouAreLame</ID>
	<ID>VoicesMentor\QUEST_NewQuest_rnd_01</ID>
	<ID>VoicesMentor\QUEST_NewQuest_rnd_02</ID>
	<ID>VoicesMentor\QUEST_NewQuest_rnd_03</ID>
	<ID>VoicesMentor\QUEST_NewQuest_rnd_04</ID>
	<ID>VoicesMentor\QUEST_NewQuest_rnd_05</ID>
	<ID>VoicesMentor\REASON_SettlerBlessed</ID>
	<ID>VoicesMentor\REASON_SettlerExpelled</ID>
	<ID>VoicesMentor\REASON_SettlerForcedToWork</ID>
	<ID>VoicesMentor\REASON_SettlerHasNoWorkPlaces</ID>
	<ID>VoicesMentor\REASON_SettlerLowTaxes</ID>
	<ID>VoicesMentor\REASON_SettlerToHighTaxes</ID>
	<ID>VoicesMentor\RESEARCH_ResearchReady_rnd_01</ID>
	<ID>VoicesMentor\RESEARCH_ResearchReady_rnd_02</ID>
	<ID>VoicesMentor\RESEARCH_ResearchReady_rnd_03</ID>
	<ID>VoicesMentor\RESEARCH_ResearchReady_rnd_04</ID>
	<ID>VoicesMentor\RESEARCH_ResearchReady_rnd_05</ID>
	<ID>VoicesMentor\RESEARCH_ResearchReady_rnd_06</ID>
	<ID>VoicesMentor\RESEARCH_ResearchReady_rnd_07</ID>
	<ID>VoicesMentor\RESEARCH_ResearchReady_rnd_08</ID>
	<ID>VoicesMentor\SAD_Alchemist</ID>
	<ID>VoicesMentor\SAD_Brickworker</ID>
	<ID>VoicesMentor\SAD_Engineer</ID>
	<ID>VoicesMentor\SAD_Farmer</ID>
	<ID>VoicesMentor\SAD_Miner</ID>
	<ID>VoicesMentor\SAD_Priest</ID>
	<ID>VoicesMentor\SAD_Sawmillworker</ID>
	<ID>VoicesMentor\SAD_Scholar</ID>
	<ID>VoicesMentor\SAD_Settler</ID>
	<ID>VoicesMentor\SAD_Smelter</ID>
	<ID>VoicesMentor\SAD_Smith</ID>
	<ID>VoicesMentor\SAD_Stonecutter</ID>
	<ID>VoicesMentor\SAD_Trader</ID>
	<ID>VoicesMentor\SAD_Treasurer</ID>
	<ID>VoicesMentor\TRADE_DealClosed_rnd_01</ID>
	<ID>VoicesMentor\TRADE_DealClosed_rnd_02</ID>
	<ID>VoicesMentor\TRADE_DealClosed_rnd_03</ID>
	<ID>VoicesMentor\TRADE_DealClosed_rnd_04</ID>
	<ID>VoicesMentor\TRADE_DealClosed_rnd_05</ID>
	<ID>VoicesMentor\TRADE_SendResourcesClay</ID>
	<ID>VoicesMentor\TRADE_SendResourcesGold</ID>
	<ID>VoicesMentor\TRADE_SendResourcesIron</ID>
	<ID>VoicesMentor\TRADE_SendResourcesStone</ID>
	<ID>VoicesMentor\TRADE_SendResourcesSulfur</ID>
	<ID>VoicesMentor\TRADE_SendResourcesWood</ID>
	<ID>VoicesMentor\UPGRADE_UpgardeHeadquarter1Available</ID>
	<ID>VoicesMentor\UPGRADE_UpgardeHeadquarter2Available</ID>
	<ID>VoicesMentor\UPGRADE_UpgradeReady_rnd_01</ID>
	<ID>VoicesMentor\UPGRADE_UpgradeReady_rnd_02</ID>
	<ID>VoicesMentor\UPGRADE_UpgradeReady_rnd_03</ID>
	<ID>VoicesMentor\UPGRADE_UpgradeReady_rnd_04</ID>
	<ID>VoicesMentor\UPGRADE_UpgradeReady_rnd_05</ID>
	<ID>VoicesMentor\VC_OnlySomeMinutesLeft_rnd_01</ID>
	<ID>VoicesMentor\VC_OnlySomeMinutesLeft_rnd_02</ID>
	<ID>VoicesMentor\VC_YouHaveLost_rnd_01</ID>
	<ID>VoicesMentor\VC_YouHaveLost_rnd_02</ID>
	<ID>VoicesMentor\VC_YouHaveWon_rnd_01</ID>
	<ID>VoicesMentor\VC_YouHaveWon_rnd_02</ID>
	<ID>VoicesMentor\VC_YourTeamHasLost_rnd_01</ID>
	<ID>VoicesMentor\VC_YourTeamHasLost_rnd_02</ID>
	<ID>VoicesMentor\VC_YourTeamHasWon_rnd_01</ID>
	<ID>VoicesMentor\VC_YourTeamHasWon_rnd_02</ID>
	<ID>VoicesMentor\WEATHER_Rain_rnd_01</ID>
	<ID>VoicesMentor\WEATHER_Rain_rnd_02</ID>
	<ID>VoicesMentor\WEATHER_Rain_rnd_03</ID>
	<ID>VoicesMentor\WEATHER_Rain_rnd_04</ID>
	<ID>VoicesMentor\WEATHER_RainForecast_rnd_01</ID>
	<ID>VoicesMentor\WEATHER_RainForecast_rnd_02</ID>
	<ID>VoicesMentor\WEATHER_Sommer_rnd_01</ID>
	<ID>VoicesMentor\WEATHER_Sommer_rnd_02</ID>
	<ID>VoicesMentor\WEATHER_Sommer_rnd_03</ID>
	<ID>VoicesMentor\WEATHER_Sommer_rnd_04</ID>
	<ID>VoicesMentor\WEATHER_SommerForecast_rnd_01</ID>
	<ID>VoicesMentor\WEATHER_SommerForecast_rnd_02</ID>
	<ID>VoicesMentor\WEATHER_Winter_rnd_01</ID>
	<ID>VoicesMentor\WEATHER_Winter_rnd_02</ID>
	<ID>VoicesMentor\WEATHER_Winter_rnd_03</ID>
	<ID>VoicesMentor\WEATHER_Winter_rnd_04</ID>
	<ID>VoicesMentor\WEATHER_WinterForecast_rnd_01</ID>
	<ID>VoicesMentor\WEATHER_WinterForecast_rnd_02</ID>


	<ID>VoicesMentorHelp\ACTION_ExtraDuties</ID>
	<ID>VoicesMentorHelp\BUILDING_AlchemistsHut</ID>
	<ID>VoicesMentorHelp\BUILDING_Ballistatower</ID>
	<ID>VoicesMentorHelp\BUILDING_Bank</ID>
	<ID>VoicesMentorHelp\BUILDING_Barracks</ID>
	<ID>VoicesMentorHelp\BUILDING_Beautification</ID>
	<ID>VoicesMentorHelp\BUILDING_BrickmakersHut</ID>
	<ID>VoicesMentorHelp\BUILDING_Cannontower</ID>
	<ID>VoicesMentorHelp\BUILDING_Chapel</ID>
	<ID>VoicesMentorHelp\BUILDING_ClayPit</ID>
	<ID>VoicesMentorHelp\BUILDING_College</ID>
	<ID>VoicesMentorHelp\BUILDING_Farm</ID>
	<ID>VoicesMentorHelp\BUILDING_Foundry</ID>
	<ID>VoicesMentorHelp\BUILDING_Headquarter</ID>
	<ID>VoicesMentorHelp\BUILDING_IronPit</ID>
	<ID>VoicesMentorHelp\BUILDING_Marketplace</ID>
	<ID>VoicesMentorHelp\BUILDING_Mill</ID>
	<ID>VoicesMentorHelp\BUILDING_Mines</ID>
	<ID>VoicesMentorHelp\BUILDING_Residence</ID>
	<ID>VoicesMentorHelp\BUILDING_SawMill</ID>
	<ID>VoicesMentorHelp\BUILDING_ShootingRange</ID>
	<ID>VoicesMentorHelp\BUILDING_Smithy</ID>
	<ID>VoicesMentorHelp\BUILDING_Stables</ID>
	<ID>VoicesMentorHelp\BUILDING_StonemasonsHut</ID>
	<ID>VoicesMentorHelp\BUILDING_StonePit</ID>
	<ID>VoicesMentorHelp\BUILDING_Storehouse</ID>
	<ID>VoicesMentorHelp\BUILDING_SulfurPit</ID>
	<ID>VoicesMentorHelp\BUILDING_VillageCenter</ID>
	<ID>VoicesMentorHelp\BUILDING_Watchtower</ID>
	<ID>VoicesMentorHelp\BUILDING_WeatherPlant</ID>
	<ID>VoicesMentorHelp\BUILDING_WeatherTower</ID>
	<ID>VoicesMentorHelp\GENERAL_Help01</ID>
	<ID>VoicesMentorHelp\GENERAL_Help02</ID>
	<ID>VoicesMentorHelp\GENERAL_Help03</ID>
	<ID>VoicesMentorHelp\GENERAL_Help04</ID>
	<ID>VoicesMentorHelp\GENERAL_Help05</ID>
	<ID>VoicesMentorHelp\GENERAL_Help06</ID>
	<ID>VoicesMentorHelp\GENERAL_Help07</ID>
	<ID>VoicesMentorHelp\GENERAL_Help08</ID>
	<ID>VoicesMentorHelp\GENERAL_Help09</ID>
	<ID>VoicesMentorHelp\GENERAL_Help10</ID>
	<ID>VoicesMentorHelp\GENERAL_Help11</ID>
	<ID>VoicesMentorHelp\GENERAL_Help12</ID>
	<ID>VoicesMentorHelp\GENERAL_Help13</ID>
	<ID>VoicesMentorHelp\GENERAL_Help14</ID>
	<ID>VoicesMentorHelp\GENERAL_Help15</ID>
	<ID>VoicesMentorHelp\GENERAL_Help16</ID>
	<ID>VoicesMentorHelp\GENERAL_Help17</ID>
	<ID>VoicesMentorHelp\GENERAL_Help18</ID>
	<ID>VoicesMentorHelp\GENERAL_Help19</ID>
	<ID>VoicesMentorHelp\GENERAL_Help20</ID>
	<ID>VoicesMentorHelp\GENERAL_Help21</ID>
	<ID>VoicesMentorHelp\GENERAL_Help22</ID>
	<ID>VoicesMentorHelp\GENERAL_Help23</ID>
	<ID>VoicesMentorHelp\GENERAL_Help24</ID>
	<ID>VoicesMentorHelp\GENERAL_Help25</ID>
	<ID>VoicesMentorHelp\GENERAL_Help26</ID>
	<ID>VoicesMentorHelp\GENERAL_Help27</ID>
	<ID>VoicesMentorHelp\GENERAL_Help28</ID>
	<ID>VoicesMentorHelp\GENERAL_Help29</ID>
	<ID>VoicesMentorHelp\GENERAL_Help30</ID>
	<ID>VoicesMentorHelp\GENERAL_Help31</ID>
	<ID>VoicesMentorHelp\GENERAL_Help32</ID>
	<ID>VoicesMentorHelp\GENERAL_Help33</ID>
	
	<ID>VoicesMentorHelp\TECHNOLOGIES_AlchemistsHut</ID>
	<ID>VoicesMentorHelp\TECHNOLOGIES_Bank</ID>
	<ID>VoicesMentorHelp\TECHNOLOGIES_College</ID>
	<ID>VoicesMentorHelp\TECHNOLOGIES_Headquarter</ID>
	<ID>VoicesMentorHelp\TECHNOLOGIES_MilitaryBuildings</ID>
	<ID>VoicesMentorHelp\TECHNOLOGIES_SawMill</ID>
	<ID>VoicesMentorHelp\TECHNOLOGIES_Smithy</ID>
	<ID>VoicesMentorHelp\TECHNOLOGIES_StonemasonsHut</ID>
	<ID>VoicesMentorHelp\TECHNOLOGIES_VillageCenter</ID>
	<ID>VoicesMentorHelp\UNIT_Archer</ID>
	<ID>VoicesMentorHelp\UNIT_Ari</ID>
	<ID>VoicesMentorHelp\UNIT_Cannon</ID>
	<ID>VoicesMentorHelp\UNIT_Dario</ID>
	<ID>VoicesMentorHelp\UNIT_Erec</ID>
	<ID>VoicesMentorHelp\UNIT_HeavyCavalry</ID>
	<ID>VoicesMentorHelp\UNIT_Helias</ID>
	<ID>VoicesMentorHelp\UNIT_Heroes</ID>
	<ID>VoicesMentorHelp\UNIT_Kerberos</ID>
	<ID>VoicesMentorHelp\UNIT_LeadersGeneral</ID>
	<ID>VoicesMentorHelp\UNIT_LightCavalry</ID>
	<ID>VoicesMentorHelp\UNIT_MarydeMortfichet</ID>
	<ID>VoicesMentorHelp\UNIT_Militia</ID>
<!--	<ID>VoicesMentorHelp\UNIT_NPC</ID>-->
	<ID>VoicesMentorHelp\UNIT_Pilgrim</ID>
	<ID>VoicesMentorHelp\UNIT_Salim</ID>
	<ID>VoicesMentorHelp\UNIT_Spearman</ID>
	<ID>VoicesMentorHelp\UNIT_Swordsman</ID>
	<ID>VoicesMentorHelp\UNIT_Varg</ID>
	<ID>VoicesMentorHelp\UNIT_Workers</ID>

	
	
	<ID>AmbientSounds\campfire_rnd_1</ID>
    <ID>AmbientSounds\campfire_rnd_2</ID>
    <ID>AmbientSounds\campfire_rnd_3</ID>
    <ID>AmbientSounds\campfire_rnd_4</ID>
    <ID>AmbientSounds\campfire_rnd_5</ID>
    <ID>AmbientSounds\forest_daytime_rnd_1</ID>
    <ID>AmbientSounds\forest_daytime_rnd_2</ID>
    <ID>AmbientSounds\forest_daytime_rnd_3</ID>
    <ID>AmbientSounds\forest_daytime_rnd_4</ID>
    <ID>AmbientSounds\forest_daytime_rnd_5</ID>
    <ID>AmbientSounds\swamp_frogs_rnd_1</ID>
    <ID>AmbientSounds\swamp_frogs_rnd_2</ID>
    <ID>AmbientSounds\swamp_frogs_rnd_3</ID>
    <ID>AmbientSounds\swamp_frogs_rnd_4</ID>
    <ID>AmbientSounds\swamp_frogs_rnd_5</ID>
    <ID>AmbientSounds\water_shore_1</ID>
    <ID>AmbientSounds\water_shore_2</ID>
    <ID>AmbientSounds\water_shore_3</ID>
    <ID>AmbientSounds\water_shore_4</ID>
    <ID>AmbientSounds\water_shore_5</ID>
    <ID>AmbientSounds\water_river_small_rnd_1</ID>
    <ID>AmbientSounds\water_river_small_rnd_2</ID>   
    <ID>AmbientSounds\water_river_small_rnd_3</ID>
    <ID>AmbientSounds\water_river_small_rnd_4</ID>
    <ID>AmbientSounds\water_river_small_rnd_5</ID>
    <ID>AmbientSounds\waterfall_rnd_1</ID>
    <ID>AmbientSounds\waterfall_rnd_2</ID>   
    <ID>AmbientSounds\waterfall_rnd_3</ID>
    <ID>AmbientSounds\waterfall_rnd_4</ID>
    <ID>AmbientSounds\waterfall_rnd_5</ID>
    <ID>AmbientSounds\wind_mountain_rnd_1</ID>    
    <ID>AmbientSounds\wind_mountain_rnd_2</ID>   
    <ID>AmbientSounds\wind_mountain_rnd_3</ID>
    <ID>AmbientSounds\wind_mountain_rnd_4</ID>
    <ID>AmbientSounds\wind_mountain_rnd_5</ID>
	<ID>AmbientSounds\lake_rnd_1</ID> 
	<ID>AmbientSounds\lake_rnd_2</ID> 
	<ID>AmbientSounds\lake_rnd_3</ID> 
	<ID>AmbientSounds\lake_rnd_4</ID> 
	<ID>AmbientSounds\meadow_rnd_1</ID>
	<ID>AmbientSounds\meadow_rnd_2</ID>
	<ID>AmbientSounds\meadow_rnd_3</ID>
	<ID>AmbientSounds\meadow_rnd_4</ID>
	<ID>AmbientSounds\meadow_rnd_5</ID>
	<ID>AmbientSounds\ocean_rnd_1</ID>
	<ID>AmbientSounds\ocean_rnd_2</ID>
	<ID>AmbientSounds\ocean_rnd_3</ID>
	<ID>AmbientSounds\ocean_rnd_4</ID>
	<ID>AmbientSounds\oceanshore_rnd_1</ID>
	<ID>AmbientSounds\oceanshore_rnd_2</ID>
	<ID>AmbientSounds\oceanshore_rnd_3</ID>
	<ID>AmbientSounds\oceanshore_rnd_4</ID>
	<ID>AmbientSounds\rainheavy</ID>
	<ID>AmbientSounds\rainlight</ID>
	<ID>AmbientSounds\rainmedium</ID>
	<ID>AmbientSounds\wind_rnd_1</ID>
	<ID>AmbientSounds\wind_rnd_2</ID>
	<ID>AmbientSounds\wind_rnd_3</ID>
	<ID>AmbientSounds\wind_rnd_4</ID>
	<ID>AmbientSounds\wind_rnd_5</ID>
	<ID>AmbientSounds\winter_rnd_1</ID>
	<ID>AmbientSounds\winter_rnd_2</ID>
	<ID>AmbientSounds\winter_rnd_3</ID>
	<ID>AmbientSounds\winter_rnd_4</ID>
	<ID>AmbientSounds\winter_rnd_5</ID>
	
	<!--Inside of Buildings-->	
	
	<ID>Buildings\Farm</ID>
	<ID>Buildings\Market</ID>
	<ID>Buildings\Monastery</ID>
	<ID>Buildings\SO_WindMill1</ID>
	<ID>Buildings\SO_Foundry1</ID>	
<!--	<ID>Buildings\SO_Weathermachine1</ID>-->
	<ID>Buildings\SO_BrickWorks_OvenDoor1</ID>
	<ID>Buildings\SO_BrickWorks_Bellow1</ID>
	<ID>Buildings\SO_BrickWorks_Table1</ID>
	<ID>Buildings\SO_Alchemist_Blubber1</ID>
	<ID>Buildings\SO_Alchemist_Ventil1</ID>
	<ID>Buildings\SO_AlchemistWheel_rnd_1</ID>
	<ID>Buildings\SO_AlchemistWheel_rnd_2</ID>
	<ID>Buildings\SO_AlchemistPump</ID>
	<ID>Buildings\SO_AlchemistBlubber_rnd_1</ID>
	<ID>Buildings\SO_AlchemistBlubber_rnd_2</ID>
	<ID>Buildings\SO_SawmillBoleRoll</ID>
	<ID>Buildings\SO_SawmillLeverOff</ID>
	<ID>Buildings\SO_SawmillLeverOn</ID>
	<ID>Buildings\SO_SawmillSaw2_rnd_1</ID>
	<ID>Buildings\SO_SawmillSaw2_rnd_2</ID>
	<ID>Buildings\SO_SawmillWaterWheel_rnd_1</ID>
	<ID>Buildings\SO_SawmillWaterWheel_rnd_2</ID>
	<ID>Buildings\</ID>
	<ID>Buildings\</ID>
	
	
	
	
	<ID>Buildings\SO_SawMill1</ID>	
	<ID>Buildings\SO_SawMill2</ID>		
	<ID>Buildings\SO_SulfurmineWheel_rnd_1</ID>
	<ID>Buildings\SO_SulfurmineWheel_rnd_2</ID>
	<ID>Buildings\SO_SulfurmineWeights</ID>
	<ID>Buildings\SO_SulfurminePlatform</ID>
	<ID>Buildings\SO_SulfurmineCrunch_rnd_2</ID>
	<ID>Buildings\SO_SulfurmineCrunch_rnd_1</ID>
	<ID>Buildings\SO_SulfurmineBelt</ID>
	<ID>Buildings\SO_ClaymineLadder_rnd_1</ID>
	<ID>Buildings\SO_ClaymineLadder_rnd_2</ID>
	<ID>Buildings\SO_ClaymineLadder_rnd_3</ID>
	<ID>Buildings\SO_ClaymineLadder_rnd_4</ID>
	<ID>Buildings\SO_ClaymineBuckets_rnd_1</ID>
	<ID>Buildings\SO_ClaymineBuckets_rnd_2</ID>
	<ID>Buildings\SO_ClaymineBigwheel_rnd_2</ID>
	<ID>Buildings\SO_ClaymineBigwheel_rnd_1</ID>
	<ID>Buildings\SO_IronmineSteam</ID>
	<ID>Buildings\SO_IronmineBarrel_rnd_1</ID>
	<ID>Buildings\SO_IronmineBarrel_rnd_2</ID>
	<ID>Buildings\SO_IronmineMelt_rnd_1</ID>
	<ID>Buildings\SO_IronmineMelt_rnd_2</ID>
	<ID>Buildings\SO_IronminePlatform</ID>
	<ID>Buildings\SO_IronmineWheel_rnd_1</ID>
	<ID>Buildings\SO_IronmineWheel_rnd_2</ID>
	<ID>Buildings\SO_StonemineCraneDangle</ID>
	<ID>Buildings\SO_StonemineCraneDown</ID>
	<ID>Buildings\SO_StonemineCraneSide</ID>
	<ID>Buildings\SO_StonemineCraneUp</ID>
<!--	<ID>Buildings\<ID>
	<ID>Buildings\<ID>
	<ID>Buildings\<ID>
	<ID>Buildings\<ID>
	<ID>Buildings\<ID>
	<ID>Buildings\<ID>
	<ID>Buildings\<ID>
	<ID>Buildings\<ID>
	<ID>Buildings\<ID>
	<ID>Buildings\<ID>
	<ID>Buildings\<ID>
	<ID>Buildings\<ID>-->

	
	<!--BuildingSounds OnKlick-->	
	<ID>OnKlick\PB_Alchemist1</ID>
	<ID>OnKlick\PB_Alchemist2</ID>
	<ID>OnKlick\PB_Archery1</ID>
	<ID>OnKlick\PB_Archery2</ID>
	<ID>OnKlick\PB_Bank1</ID>
	<ID>OnKlick\PB_Bank2</ID>
	<ID>OnKlick\PB_Barracks1</ID>
	<ID>OnKlick\PB_Barracks2</ID>
	<ID>OnKlick\PB_Blacksmith1</ID>
	<ID>OnKlick\PB_Blacksmith2</ID>
	<ID>OnKlick\PB_Blacksmith3</ID>
	<ID>OnKlick\PB_Brickworks1</ID>
	<ID>OnKlick\PB_Brickworks2</ID>
	<ID>OnKlick\PB_Headquarters1</ID>
	<ID>OnKlick\PB_Headquarters2</ID>
	<ID>OnKlick\PB_Headquarters3</ID>
	<ID>OnKlick\PB_ClayMine1</ID>
	<ID>OnKlick\PB_ClayMine2</ID>
	<ID>OnKlick\PB_ClayMine3</ID>
	<ID>OnKlick\PB_Farm1</ID>
	<ID>OnKlick\PB_Farm2</ID>
	<ID>OnKlick\PB_Farm3</ID>
	<ID>OnKlick\PB_Foundry1</ID>
	<ID>OnKlick\PB_Foundry2</ID>
	<ID>OnKlick\PB_IronMine1</ID>
	<ID>OnKlick\PB_IronMine2</ID>
	<ID>OnKlick\PB_IronMine3</ID>
	<ID>OnKlick\PB_Market1</ID>
	<ID>OnKlick\PB_Market2</ID>
	<ID>OnKlick\PB_Monastery1</ID>
	<ID>OnKlick\PB_Monastery2</ID>
	<ID>OnKlick\PB_Monastery3</ID>
	<ID>OnKlick\PB_Outpost</ID>
	<ID>OnKlick\PB_PowerPlant1</ID>
	<ID>OnKlick\PB_Residence1</ID>
	<ID>OnKlick\PB_Residence2</ID>
	<ID>OnKlick\PB_Residence3</ID>
	<ID>OnKlick\PB_Sawmill1</ID>
	<ID>OnKlick\PB_Sawmill2</ID>
	<ID>OnKlick\PB_Stable1</ID>
	<ID>OnKlick\PB_Stable2</ID>
	<ID>OnKlick\PB_StoneMason1</ID>
	<ID>OnKlick\PB_StoneMason2</ID>
	<ID>OnKlick\PB_StoneMine1</ID>
	<ID>OnKlick\PB_StoneMine2</ID>
	<ID>OnKlick\PB_StoneMine3</ID>
	<ID>OnKlick\PB_SulfurMine1</ID>
	<ID>OnKlick\PB_SulfurMine2</ID>
	<ID>OnKlick\PB_SulfurMine3</ID>
	<ID>OnKlick\PB_Tower1</ID>
	<ID>OnKlick\PB_Tower2</ID>
	<ID>OnKlick\PB_Tower3</ID>
	<ID>OnKlick\PB_University1</ID>
	<ID>OnKlick\PB_University2</ID>
	<ID>OnKlick\PB_VillageCenter1</ID>
	<ID>OnKlick\PB_VillageCenter2</ID>
	<ID>OnKlick\PB_VillageCenter3</ID>
	<ID>OnKlick\PB_Weathermachine</ID>
	<ID>OnKlick\PB_WeatherTower1</ID>
	
	
	<!--Heroes on click sounds-->	
	<ID>OnKlick\Select_ari</ID>
	<ID>OnKlick\Select_dario</ID>
	<ID>OnKlick\Select_erec</ID>
	<ID>OnKlick\Select_helias</ID>
	<ID>OnKlick\Select_kerberos</ID>
	<ID>OnKlick\Select_mary_de_mortfichet</ID>
	<ID>OnKlick\Select_pilgrim</ID>
	<ID>OnKlick\Select_salim</ID>
	<ID>OnKlick\Select_varg</ID>
	
	
	<!--Military Sounds-->	
    <ID>Military\SO_BallistaFire_rnd_1</ID>   
    <ID>Military\SO_BallistaFire_rnd_2</ID>   
    <ID>Military\SO_BallistaFire_rnd_3</ID>   
    <ID>Military\SO_BallistaHit_rnd_1</ID>   
    <ID>Military\SO_BallistaHit_rnd_2</ID>   
    <ID>Military\SO_BallistaHit_rnd_3</ID>   
    <ID>Military\SO_Cannon_rnd_1</ID> 
    <ID>Military\SO_Cannon_rnd_2</ID> 
    <ID>Military\SO_Cannon_rnd_3</ID> 
    <ID>Military\SO_CannonHit_rnd_1</ID> 
    <ID>Military\SO_CannonHit_rnd_2</ID> 
    <ID>Military\SO_CannonHit_rnd_3</ID> 
    <ID>Military\SO_CannonTowerFire_rnd_1</ID> 
    <ID>Military\SO_CannonTowerFire_rnd_2</ID> 
    <ID>Military\SO_CannonTowerFire_rnd_3</ID>     
    <ID>Military\SO_SoldierBow_rnd_1</ID> 
    <ID>Military\SO_SoldierBow_rnd_2</ID> 
    <ID>Military\SO_SoldierBow_rnd_3</ID> 
    <ID>Military\SO_SoldierBow_rnd_4</ID> 
    <ID>Military\SO_SoldierBow_rnd_5</ID> 
    <ID>Military\SO_SoldierMace_rnd_1</ID> 
    <ID>Military\SO_SoldierMace_rnd_2</ID> 
    <ID>Military\SO_SoldierMace_rnd_3</ID> 
    <ID>Military\SO_SoldierMace_rnd_4</ID> 
    <ID>Military\SO_SoldierMace_rnd_5</ID> 
    <ID>Military\SO_SoldierMace_rnd_6</ID> 
    <ID>Military\SO_SoldierPolearm_rnd_1</ID> 
    <ID>Military\SO_SoldierPolearm_rnd_2</ID> 
    <ID>Military\SO_SoldierPolearm_rnd_3</ID> 
    <ID>Military\SO_SoldierPolearm_rnd_4</ID> 
    <ID>Military\SO_SoldierPolearm_rnd_5</ID> 
    <ID>Military\SO_SoldierPolearm_rnd_6</ID> 
    <ID>Military\SO_SoldierSword_rnd_1</ID> 
    <ID>Military\SO_SoldierSword_rnd_2</ID> 
    <ID>Military\SO_SoldierSword_rnd_3</ID> 
    <ID>Military\SO_SoldierSword_rnd_4</ID> 
    <ID>Military\SO_SoldierSword_rnd_5</ID> 
    
    <ID>Military\so_serfFist_rnd_1</ID>
    <ID>Military\so_serfFist_rnd_2</ID>
    <ID>Military\so_serfFist_rnd_3</ID>
    <ID>Military\so_serfFist_rnd_4</ID>
    
	<!--<ID>Military\SO_SoldierSword_rnd_6</ID> -->

	<!--Misc Sounds-->	
	<ID>Misc\Chat</ID>
	<ID>Misc\Chat2</ID> 
	<ID>Misc\Countdown1</ID> 	
	<ID>Misc\Countdown2</ID> 	
	<ID>Misc\Countdown3</ID> 	
	<ID>Misc\Countdown4</ID> 	
	<ID>Misc\Countdown5</ID> 	
	<ID>Misc\Countdown6</ID> 	
	<ID>Misc\Countdown7</ID> 	
	<ID>Misc\Countdown8</ID> 	
	<ID>Misc\Countdown9</ID> 	
	<ID>Misc\Countdown10</ID> 	
    <ID>Misc\SO_WorkMetal_rnd_1</ID> 
    <ID>Misc\SO_WorkMetal_rnd_2</ID> 
    <ID>Misc\SO_WorkMetal_rnd_3</ID> 
    <ID>Misc\SO_WorkMetal_rnd_4</ID> 
    <ID>Misc\SO_WorkStone_rnd_1</ID> 
    <ID>Misc\SO_WorkStone_rnd_2</ID> 
    <ID>Misc\SO_WorkStone_rnd_3</ID> 
    <ID>Misc\SO_WorkStone_rnd_4</ID> 
    <ID>Misc\SO_WorkWood_rnd_1</ID> 
    <ID>Misc\SO_WorkWood_rnd_2</ID> 
    <ID>Misc\SO_WorkWood_rnd_3</ID> 
    <ID>Misc\SO_WorkWood_rnd_4</ID> 
    <ID>Misc\SO_BuildMetal_rnd_1</ID> 
    <ID>Misc\SO_BuildMetal_rnd_2</ID> 
    <ID>Misc\SO_BuildMetal_rnd_3</ID> 
    <ID>Misc\SO_BuildWood_rnd_1</ID> 
    <ID>Misc\SO_BuildWood_rnd_2</ID> 
    <ID>Misc\SO_BuildWood_rnd_3</ID> 
    <ID>Misc\SO_BuildWood_rnd_4</ID> 
    <ID>Misc\SO_BuildWood_rnd_5</ID> 

	<ID>VoicesMentorHelp\BUILDING_Barracks</ID> 
	<ID>VoicesMentorHelp\BUILDING_Headquarter</ID> 
	<ID>VoicesMentorHelp\BUILDING_Smithy</ID> 
	<ID>VoicesMentorHelp\UNIT_Swordsman</ID> 
	<ID>VoicesMentorHelp\ACTION_Alert</ID>
	<ID>VoicesMentorHelp\ACTION_ExpelSettler</ID>
	<ID>VoicesMentorHelp\ACTION_Bless</ID>
			
    <ID>Selection_global</ID>
    <ID>klick_rnd_1</ID>
    <ID>LevyTaxes</ID>
    <ID>fanfare</ID>
    <ID>Coiner01</ID>

	<!--Community Patch-->
	<ID>Smith01</ID>
	<ID>Buildings\so_weathermachineelectro</ID>
	<ID>Misc\so_buildingonfire_loop_1</ID>
	<ID>Misc\so_buildingonfire_loop_2</ID>
	<ID>Misc\so_buildingonfire_loop_3</ID>
	<ID>Military\so_stepsoldier_rnd_1</ID>
	<ID>Military\so_stepsoldier_rnd_2</ID>
	<ID>Military\so_stepsoldier_rnd_3</ID>
	<ID>Military\so_stepsoldier_rnd_4</ID>
	<ID>Military\so_stephorse_rnd_1</ID>
	<ID>Military\so_stephorse_rnd_2</ID>
	<ID>Military\so_stephorse_rnd_3</ID>
	<ID>Military\so_stephorse_rnd_4</ID>

	<ID>AmbientSounds\Wolf_rnd_1</ID>
	<ID>AmbientSounds\Wolf_rnd_2</ID>
	<ID>AmbientSounds\bear_idle01</ID>
	<ID>AmbientSounds\bear_idle02</ID>
	<ID>AmbientSounds\bear_idle03</ID>
	<ID>AmbientSounds\Sheep_rnd_1</ID>
	<ID>AmbientSounds\Sheep_rnd_2</ID>
	<ID>AmbientSounds\Sheep_rnd_3</ID>

	<ID>VoicesHero0\Scout_Attack_rnd_01</ID>
	<ID>VoicesHero0\Scout_Attack_rnd_02</ID>
	<ID>VoicesHero0\Scout_Attack_rnd_03</ID>
	<ID>VoicesHero0\Scout_Attack_rnd_04</ID>
	<ID>VoicesHero0\Scout_Attack_rnd_05</ID>
	<ID>VoicesHero0\Scout_NO_rnd_01</ID>
	<ID>VoicesHero0\Scout_NO_rnd_02</ID>
	<ID>VoicesHero0\Scout_NO_rnd_03</ID>
	<ID>VoicesHero0\Scout_NO_rnd_04</ID>
	<ID>VoicesHero0\Scout_NO_rnd_05</ID>
	<ID>VoicesHero0\Scout_NO_rnd_06</ID>
	<ID>VoicesHero0\Scout_NO_rnd_07</ID>
	<ID>VoicesHero0\Scout_Yes_rnd_01</ID>
	<ID>VoicesHero0\Scout_Yes_rnd_02</ID>
	<ID>VoicesHero0\Scout_Yes_rnd_03</ID>
	<ID>VoicesHero0\Scout_Yes_rnd_04</ID>
	<ID>VoicesHero0\Scout_Yes_rnd_05</ID>
	<ID>VoicesHero0\Scout_Yes_rnd_06</ID>
	<ID>VoicesHero0\Scout_Yes_rnd_07</ID>
	<ID>VoicesHero0\Scout_Yes_rnd_08</ID>
	<ID>VoicesHero0\Scout_Yes_rnd_09</ID>
	<ID>VoicesHero0\Scout_Yes_rnd_10</ID>
	<ID>VoicesHero0\Scout_Yes_rnd_10</ID>
	<ID>VoicesHero0\Scout_FunnyComment_rnd_04</ID>

	<ID>Misc\so_signalhorn</ID>
	<ID>Misc\SO_Die_Female_rnd_1</ID>
	<ID>Animals\SO_Wolf_Die_rnd_1</ID>
	<ID>Animals\SO_Bear_Die_rnd_1</ID>
	<ID>Animals\SO_Bear_rnd_1</ID>
	<ID>Animals\SO_Bear_rnd_2</ID>
	<ID>Animals\SO_Wolf_rnd_1</ID>
	<ID>Animals\SO_Wolf_rnd_2</ID>
	<ID>Misc\so_treefall_rnd_1</ID>
	<ID>Misc\so_treefall_rnd_2</ID>
	<ID>Military\SO_ArrowHit_rnd_1</ID>
	<ID>Military\SO_ArrowHit_rnd_2</ID>
	<ID>Military\SO_ArrowHit_rnd_3</ID>
	<ID>Military\SO_ArrowHit_rnd_4</ID>
	<ID>Military\SO_ArrowHit_rnd_5</ID>
	<ID>Military\SO_ArrowHit_rnd_6</ID>
	<ID>Military\SO_ArrowHit_rnd_7</ID>
	<ID>Military\SO_Die_rnd_1</ID>
	<ID>Military\SO_Die_rnd_2</ID>
	<ID>Military\SO_Die_rnd_3</ID>
	<ID>Military\SO_Die_rnd_4</ID>
	<ID>Military\SO_Die_rnd_5</ID>
	<ID>Military\SO_Die_rnd_6</ID>
	<ID>Military\SO_Die_rnd_7</ID>
	<ID>Military\SO_Die_rnd_8</ID>
	<ID>Military\SO_Die_rnd_9</ID>
</root>
    
    
    
    
    
