<?xml version="1.0" encoding="utf-8" ?>
<root>
 <NameKey>AOMapDescription/CM02_07_FleeOrFight_name</NameKey>
 <DescKey>AOMapDescription/CM02_07_FleeOrFight_desc</DescKey>
 <Name></Name>
 <Desc></Desc>
 <SizeX>641</SizeX>
 <SizeY>641</SizeY>
 <MPFlag>false</MPFlag>
 <MPPlayerCount>0</MPPlayerCount>
 <MPGameOptionFlagSet>0</MPGameOptionFlagSet>
 <MiniMapTextureName>data\graphics\Textures\GUI\MapPics\externalmap</MiniMapTextureName>
 <Key>1</Key>
 <GUID>
  <Data>045c180a-ea8f-4f9c-bfe3-0859c2504b1b</Data>
 </GUID>
</root>
